augr/__init__.py
augr/ai_client.py
augr/augmentation_service.py
augr/braintrust_client.py
augr/cli.py
augr/config.py
augr/dataset_helper.py
augr/models.py
augr/specify_model.py
augr/uninstall.py
augr-0.2.0.dist-info/METADATA
augr-0.2.0.dist-info/WHEEL
augr-0.2.0.dist-info/entry_points.txt
augr-0.2.0.dist-info/RECORD
