Metadata-Version: 2.4
Name: augr
Version: 0.2.0
Summary: AI-powered dataset augmentation tool using Braintrust proxy
Project-URL: Homepage, https://github.com/Marviel/augr
Project-URL: Repository, https://github.com/Marviel/augr
Project-URL: Issues, https://github.com/Marviel/augr/issues
Author-email: Luke Bechtel <your-email@example.com>
License: MIT
Keywords: ai,augmentation,braintrust,dataset,machine-learning
Classifier: Development Status :: 4 - Beta
Classifier: Intended Audience :: Developers
Classifier: License :: OSI Approved :: MIT License
Classifier: Programming Language :: Python :: 3
Classifier: Programming Language :: Python :: 3.8
Classifier: Programming Language :: Python :: 3.9
Classifier: Programming Language :: Python :: 3.10
Classifier: Programming Language :: Python :: 3.11
Classifier: Programming Language :: Python :: 3.12
Requires-Python: >=3.8
Requires-Dist: braintrust>=0.0.1
Requires-Dist: inquirer>=3.1.0
Requires-Dist: openai>=1.40.0
Requires-Dist: pydantic>=2.0.0
Requires-Dist: python-dotenv>=1.0.0
Provides-Extra: dev
Requires-Dist: black>=23.0.0; extra == 'dev'
Requires-Dist: build>=0.10.0; extra == 'dev'
Requires-Dist: pytest>=7.0.0; extra == 'dev'
Requires-Dist: ruff>=0.1.0; extra == 'dev'
Requires-Dist: twine>=4.0.0; extra == 'dev'
